morseutils/__init__.py
morseutils/player.py
morseutils/translator.py
morseutils-0.0.4.100.dist-info/LICENSE.txt
morseutils-0.0.4.100.dist-info/METADATA
morseutils-0.0.4.100.dist-info/WHEEL
morseutils-0.0.4.100.dist-info/top_level.txt
morseutils-0.0.4.100.dist-info/RECORD
