Metadata-Version: 2.1
Name: morseutils
Version: 0.0.4.100
Summary: A morsecode translator and player package. 
Home-page: https://github.com/jamejunj/morsecodeutils
Author: Jirakit Jirapongwanich
Author-email: jame.jpwn@gmail.com
Classifier: Programming Language :: Python :: 3
Classifier: License :: OSI Approved :: MIT License
Classifier: Operating System :: OS Independent
Requires-Python: >=3.6
License-File: LICENSE.txt
